konigle/__init__.py
konigle/cli/__init__.py
konigle/cli/authors.py
konigle/cli/blogs.py
konigle/cli/comm/__init__.py
konigle/cli/comm/audiences.py
konigle/cli/comm/base.py
konigle/cli/comm/campaigns.py
konigle/cli/comm/contacts.py
konigle/cli/comm/email.py
konigle/cli/components.py
konigle/cli/config.py
konigle/cli/connections.py
konigle/cli/design.py
konigle/cli/folders.py
konigle/cli/forms.py
konigle/cli/glossary.py
konigle/cli/images.py
konigle/cli/main.py
konigle/cli/pages.py
konigle/cli/product_images.py
konigle/cli/product_variants.py
konigle/cli/products.py
konigle/cli/projects.py
konigle/cli/site.py
konigle/cli/templates.py
konigle/cli/uploads.py
konigle/client.py
konigle/config.py
konigle/exceptions.py
konigle/filters/__init__.py
konigle/filters/base.py
konigle/filters/comm.py
konigle/filters/commerce.py
konigle/filters/core.py
konigle/filters/website.py
konigle/logging.py
konigle/managers/__init__.py
konigle/managers/base.py
konigle/managers/comm/__init__.py
konigle/managers/comm/audience.py
konigle/managers/comm/campaign.py
konigle/managers/comm/contact.py
konigle/managers/comm/email/__init__.py
konigle/managers/comm/email/account.py
konigle/managers/comm/email/channel.py
konigle/managers/comm/email/email.py
konigle/managers/comm/email/identity.py
konigle/managers/comm/email/template.py
konigle/managers/commerce/__init__.py
konigle/managers/commerce/product.py
konigle/managers/commerce/product_image.py
konigle/managers/commerce/product_variant.py
konigle/managers/core/__init__.py
konigle/managers/core/connections.py
konigle/managers/core/form.py
konigle/managers/core/media_asset.py
konigle/managers/core/upload.py
konigle/managers/website/__init__.py
konigle/managers/website/author.py
konigle/managers/website/blog.py
konigle/managers/website/component.py
konigle/managers/website/design.py
konigle/managers/website/folder.py
konigle/managers/website/glossary.py
konigle/managers/website/page.py
konigle/managers/website/site.py
konigle-0.27.0.dist-info/WHEEL
konigle-0.27.0.dist-info/entry_points.txt
konigle-0.27.0.dist-info/METADATA
konigle-0.27.0.dist-info/RECORD
