Metadata-Version: 2.3
Name: konigle
Version: 0.27.0
Summary: Python SDK for Konigle platform
Keywords: konigle,sdk,api,ecommerce,website-builder
Author: Konigle Developers
Author-email: Konigle Developers <developers@konigle.com>
Classifier: Development Status :: 4 - Beta
Classifier: Intended Audience :: Developers
Classifier: Programming Language :: Python :: 3
Classifier: Programming Language :: Python :: 3.12
Classifier: Topic :: Software Development :: Libraries :: Python Modules
Requires-Dist: click>=8.2.1
Requires-Dist: httpx>=0.28.1
Requires-Dist: pydantic[email]>=2.11.7
Requires-Python: >=3.12
Project-URL: Documentation, https://konigle.github.io/konigle-python/
Project-URL: Homepage, https://konigle.github.io/konigle-python/
Project-URL: Issues, https://github.com/konigle/konigle-python/issues
Project-URL: Repository, https://github.com/konigle/konigle-python
